MelodieFuncFlow/__init__.py
MelodieFuncFlow/__main__.py
MelodieFuncFlow/functional.py
MelodieFuncFlow-0.3.0.dist-info/LICENSE.txt
MelodieFuncFlow-0.3.0.dist-info/METADATA
MelodieFuncFlow-0.3.0.dist-info/WHEEL
MelodieFuncFlow-0.3.0.dist-info/top_level.txt
MelodieFuncFlow-0.3.0.dist-info/RECORD
