Metadata-Version: 2.1
Name: MelodieFuncFlow
Version: 0.3.0
Summary: Functional programming extension of Melodie
Home-page: https://github.com/hzyrc6011/MelodieFuncFlow
Author: Zhanyi Hou
Author-email: abm4all@outlook.com
License: MIT
Project-URL: Documentation, https://github.com/hzyrc6011/MelodieFuncFlow
Classifier: Development Status :: 4 - Beta
Classifier: Intended Audience :: Science/Research
Classifier: License :: OSI Approved :: MIT License
Classifier: Natural Language :: English
Classifier: Operating System :: Unix
Classifier: Operating System :: Microsoft :: Windows
Classifier: Programming Language :: Python :: 3.8
Classifier: Programming Language :: Python :: 3.9
Classifier: Programming Language :: Python :: 3.10
Classifier: Programming Language :: Python :: 3.11
Classifier: Programming Language :: Python :: 3.12
Classifier: Topic :: Scientific/Engineering :: Artificial Intelligence
Requires-Python: >=3.8
License-File: LICENSE.txt
